overrated_ld_stress_detector/README.md
overrated_ld_stress_detector/__init__.py
overrated_ld_stress_detector/constants.py
overrated_ld_stress_detector/main.py
overrated_ld_stress_detector/preprocessing.py
overrated_ld_stress_detector/ml/__init__.py
overrated_ld_stress_detector/ml/predict.py
overrated_ld_stress_detector/ml/pretrained_model.py
overrated_ld_stress_detector/models/__init__.py
overrated_ld_stress_detector/models/dataset_test.csv
overrated_ld_stress_detector/models/dataset_test.xlsx
overrated_ld_stress_detector/models/dataset_train.xlsx
overrated_ld_stress_detector/models/model_0.pckl
overrated_ld_stress_detector/models/model_1.pckl
overrated_ld_stress_detector/models/model_2.pckl
overrated_ld_stress_detector/models/model_3.pckl
overrated_ld_stress_detector/models/model_4.pckl
overrated_ld_stress_detector/models/nn_full.pth
overrated_ld_stress_detector/visualization/__init__.py
overrated_ld_stress_detector/visualization/utils.py
overrated_ld_stress_detector-0.1.11.data/data/overrated_ld_stress_detector/README.md
overrated_ld_stress_detector-0.1.11.data/data/overrated_ld_stress_detector/model_0.pckl
overrated_ld_stress_detector-0.1.11.data/data/overrated_ld_stress_detector/model_1.pckl
overrated_ld_stress_detector-0.1.11.data/data/overrated_ld_stress_detector/model_2.pckl
overrated_ld_stress_detector-0.1.11.data/data/overrated_ld_stress_detector/model_3.pckl
overrated_ld_stress_detector-0.1.11.data/data/overrated_ld_stress_detector/model_4.pckl
overrated_ld_stress_detector-0.1.11.data/data/overrated_ld_stress_detector/nn_full.pth
overrated_ld_stress_detector-0.1.11.dist-info/METADATA
overrated_ld_stress_detector-0.1.11.dist-info/WHEEL
overrated_ld_stress_detector-0.1.11.dist-info/top_level.txt
overrated_ld_stress_detector-0.1.11.dist-info/RECORD
