Metadata-Version: 2.1
Name: overrated-ld-stress-detector
Version: 0.1.11
Summary: Stress detection.
Home-page: https://github.com/mansasha21/overrated-ld-stress-detector
Author: Overrated team
License: MIT
Platform: UNKNOWN
Classifier: License :: OSI Approved :: MIT License
Classifier: Intended Audience :: Developers
Classifier: Intended Audience :: Science/Research
Classifier: Operating System :: OS Independent
Classifier: Programming Language :: Python
Classifier: Programming Language :: Python :: 3
Classifier: Topic :: Software Development :: Libraries
Classifier: Topic :: Software Development :: Libraries :: Python Modules
Requires-Dist: plotly
Requires-Dist: numpy
Requires-Dist: pandas
Requires-Dist: catboost
Requires-Dist: scikit-learn
Requires-Dist: torch (>=1.9.0)
